extensified/__init__.py
extensified/_extension_decorator.py
extensified-0.3.0.dist-info/LICENSE
extensified-0.3.0.dist-info/METADATA
extensified-0.3.0.dist-info/WHEEL
extensified-0.3.0.dist-info/RECORD
