Metadata-Version: 2.1
Name: extensified
Version: 0.3.0
Summary: Extension methods for Python.
Keywords: extensions,extension classes,extension methods
Author: Vasiliy Spassky
Author-email: spassky99@gmail.com
Requires-Python: >=3.9,<4.0
Classifier: Development Status :: 4 - Beta
Classifier: Intended Audience :: Developers
Classifier: License :: OSI Approved :: MIT License
Classifier: Operating System :: OS Independent
Classifier: Programming Language :: Python :: 3
Classifier: Programming Language :: Python :: 3.9
Classifier: Programming Language :: Python :: 3.10
Classifier: Programming Language :: Python :: 3.11
Classifier: Programming Language :: Python :: 3.12
Classifier: Programming Language :: Python :: 3.13
Classifier: Topic :: Software Development :: Libraries
Classifier: Typing :: Typed
Project-URL: Homepage, https://github.com/v-spassky/extensified
Project-URL: Issues, https://github.com/v-spassky/extensified/issues
Project-URL: Repository, https://github.com/v-spassky/extensified.git
